{
  "daemon": {
    "sleep": 1800
  },
  "#trace_list": "기사 목록 정보, 기사를 저장할 위치/인덱스, 슬립타임 설정",
  "trace_list": [
    {
      "host": "http://corpus.ncsoft.com:9200",
      "index": "crawler-naver-politics",
      "sleep": 10,
      "list": [
        {
          "url_frame": "https://news.naver.com/main/list.nhn?mode=LS2D&mid=shm&sid1=100&sid2=264&listType=title&date={date}&page={page}",
          "date_format": "%Y%m%d",
          "category": "정치/청와대"
        },
        {
          "url_frame": "https://news.naver.com/main/list.nhn?mode=LS2D&mid=shm&sid1=100&sid2=265&listType=title&date={date}&page={page}",
          "date_format": "%Y%m%d",
          "category": "정치/국회정당"
        },
        {
          "url_frame": "https://news.naver.com/main/list.nhn?mode=LS2D&mid=shm&sid1=100&sid2=268&listType=title&date={date}&page={page}",
          "date_format": "%Y%m%d",
          "category": "정치/북한"
        },
        {
          "url_frame": "https://news.naver.com/main/list.nhn?mode=LS2D&mid=shm&sid1=100&sid2=266&listType=title&date={date}&page={page}",
          "date_format": "%Y%m%d",
          "category": "정치/행정"
        },
        {
          "url_frame": "https://news.naver.com/main/list.nhn?mode=LS2D&mid=shm&sid1=100&sid2=267&listType=title&date={date}&page={page}",
          "date_format": "%Y%m%d",
          "category": "정치/국방외교"
        },
        {
          "url_frame": "https://news.naver.com/main/list.nhn?mode=LS2D&mid=shm&sid1=100&sid2=269&listType=title&date={date}&page={page}",
          "date_format": "%Y%m%d",
          "category": "정치/정치일반"
        },
        {
          "url_frame": "https://news.naver.com/main/main.nhn?mode=LSD&mid=shm&sid1=100&listType=title&date={date}&page={page}",
          "date_format": "%Y%m%d",
          "section": "정치"
        }
      ],
      "article": {
        "document_id": {
          "type": "query",
          "frame": "{oid}-{aid}"
        }
      },
      "post_process": [
        {
          "name": "rabbit mq 에 메세지를 보낸다.",
          "module": "rabbit_mq",
          "exchange": {
            "type": "topic",
            "name": "crawler.naver"
          },
          "host": {
            "name": "g7",
            "port": 5672,
            "user_name": "user",
            "user_password": "nlplab!"
          },
          "payload": {
            "elastic": {
              "host": "http://corpus.ncsoft.com:9200",
              "index": "corpus_process-naver-politics"
            },
            "module": [
              {
                "name": "sp/pos_tagger",
                "domain": "economy",
                "column": "html_content",
                "result": "pos_tagged"
              },
              {
                "name": "sp/ne_tagger",
                "domain": "economy",
                "column": "html_content",
                "result": "named_entity"
              },
              {
                "name": "nc/ne_tagger_v2",
                "domain": "economy",
                "column": "html_content",
                "result": "named_entity_v2"
              }
            ]
          }
        }
      ]
    }
  ]
}
