{
  "_id": "sportskhan.sports",
  "article_page": [
    {
      "tag_name": "div",
      "attr": {
        "id": "container"
      },
      "data": {
        "title": {
          "tag_name": "h1",
          "attr": {
            "id": "article_title"
          },
          "value": "text"
        },
        "author": {
          "tag_name": "p",
          "attr": {
            "class": "info_byline"
          },
          "value": "text"
        },
        "date": {
          "tag_name": "div",
          "attr": {
            "class": "byline"
          },
          "value": "text",
          "replace": [
            {
              "from": "^.+(20[0-9][0-9][.\\- :0-9]+).+$",
              "to": "\\g<1>"
            }
          ]
        },
        "html_content": {
          "tag_name": "div",
          "attr": {
            "class": "desc_body"
          },
          "value": "html"
        }
      }
    }
  ],
  "comment": "스포츠경향 야구 기사",
  "id": {
    "replace": [
      {
        "from": "^.+art_id=(.+?)[&].+$",
        "to": "\\g<1>"
      }
    ]
  },
  "page_list": {
    "index": {
      "tag_name": "a"
    },
    "next": {
      "attr": {
        "class": "next"
      },
      "tag_name": "a"
    },
    "panel": {
      "attr": {
        "class": "paging"
      },
      "tag_name": "div"
    }
  },
  "parsing_type": "",
  "query_key_mapping": {
    "page": "start"
  },
  "subject_page": {
    "attr": {
      "id": "content_sm"
    },
    "next_tag": {
      "data": {
        "title": {
          "tag_name": "a",
          "value": "text"
        },
        "url": {
          "tag_name": "a",
          "value": "href"
        }
      },
      "tag_name": "dl"
    },
    "tag_name": "div"
  }
}